LICENSE
MANIFEST.in
README.md
setup.py
Backupy/__init__.py
Backupy/backupy.py
Backupy_tool.egg-info/PKG-INFO
Backupy_tool.egg-info/SOURCES.txt
Backupy_tool.egg-info/dependency_links.txt
Backupy_tool.egg-info/requires.txt
Backupy_tool.egg-info/top_level.txt
examples/1) basic.py
examples/2) Exclude directories and files.py
examples/3) Format date or filename.py
examples/4) Change destination directory.py
examples/5) Database backup.py
tests/__init__.py
tests/test_backup.py
tests/test_backup_directory.py
tests/test_destination_directory.py
tests/test_filename.py