Metadata-Version: 2.1
Name: Backupy-tool
Version: 0.0.2
Summary: Python script for backup files, directories and databases. Save your data from loss or damage.
Home-page: https://github.com/KonstantinPankratov/Backupy
Author: Konstantin Pankratov
Author-email: hello@kopa.pw
License: MIT
Keywords: backup,backup script,backup utility,backup database,backup mysql
Platform: UNKNOWN
Classifier: Development Status :: 5 - Production/Stable
Classifier: License :: OSI Approved :: MIT License
Classifier: Programming Language :: Python :: 2
Classifier: Programming Language :: Python :: 2.7
Classifier: Programming Language :: Python :: 3
Classifier: Programming Language :: Python :: 3.5
Classifier: Programming Language :: Python :: 3.6
Classifier: Programming Language :: Python :: 3.7
Classifier: Programming Language :: Python :: 3.8
